shauto_ai/__init__.py
shauto_ai/firstFile.py
shauto_ai-0.0.1.dist-info/METADATA
shauto_ai-0.0.1.dist-info/WHEEL
shauto_ai-0.0.1.dist-info/RECORD
