Metadata-Version: 2.1
Name: shAuto-AI
Version: 0.0.1
Summary: A small sample package
License: MIT
Author: Abhishek kandari
Author-email: abhishekkandari96@gmail.com
Requires-Python: >=3.9,<4.0
Classifier: License :: OSI Approved :: MIT License
Classifier: Programming Language :: Python :: 3
Classifier: Programming Language :: Python :: 3.9
Classifier: Programming Language :: Python :: 3.10
Classifier: Programming Language :: Python :: 3.11
Classifier: Programming Language :: Python :: 3.12
Requires-Dist: beautifulsoup4 (>=4.12.3,<5.0.0)
Requires-Dist: pandas (>=2.2.2,<3.0.0)
Requires-Dist: requests (>=2.32.3,<3.0.0)
Requires-Dist: scikit-learn (>=1.5.2,<2.0.0)
Requires-Dist: selenium (>=4.24.0,<5.0.0)
Project-URL: documentation, https://github.com/Abhishekkandari96/shAuto-AI
Project-URL: homepage, https://github.com/Abhishekkandari96/shAuto-AI
Project-URL: issues, https://github.com/Abhishekkandari96/shAuto-AI/issues
Project-URL: repository, https://github.com/Abhishekkandari96/shAuto-AI
